anymap/__init__.py
anymap/anymap.py
anymap/base.py
anymap/basemaps.py
anymap/cesium.py
anymap/compare.py
anymap/deckgl.py
anymap/draw_styles.py
anymap/keplergl.py
anymap/leaflet.py
anymap/mapbox.py
anymap/maplibre.py
anymap/maplibre_widgets.py
anymap/openlayers.py
anymap/potree.py
anymap/stac.py
anymap/utils.py
anymap/static/cesium_widget.css
anymap/static/cesium_widget.js
anymap/static/deckgl_widget.css
anymap/static/deckgl_widget.js
anymap/static/keplergl_widget.css
anymap/static/keplergl_widget.js
anymap/static/leaflet_widget.css
anymap/static/leaflet_widget.js
anymap/static/mapbox_compare_widget.css
anymap/static/mapbox_compare_widget.js
anymap/static/mapbox_widget.css
anymap/static/mapbox_widget.js
anymap/static/maplibre_compare_widget.css
anymap/static/maplibre_compare_widget.js
anymap/static/maplibre_widget.css
anymap/static/maplibre_widget.js
anymap/static/openlayers_widget.css
anymap/static/openlayers_widget.js
anymap/static/potree_widget.css
anymap/static/potree_widget.js
anymap/templates/maplibre_template.html
anymap-0.11.3.dist-info/licenses/LICENSE
anymap-0.11.3.dist-info/METADATA
anymap-0.11.3.dist-info/WHEEL
anymap-0.11.3.dist-info/top_level.txt
anymap-0.11.3.dist-info/RECORD
