Metadata-Version: 2.4
Name: anymap
Version: 0.11.3
Summary: A Python package for creating interactive maps with anywidget and JavaScript mapping libraries
Author-email: Qiusheng Wu <giswqs@gmail.com>
License: MIT License
Project-URL: Homepage, https://github.com/opengeos/anymap
Keywords: anymap
Classifier: Intended Audience :: Developers
Classifier: License :: OSI Approved :: MIT License
Classifier: Natural Language :: English
Classifier: Programming Language :: Python :: 3.9
Classifier: Programming Language :: Python :: 3.10
Classifier: Programming Language :: Python :: 3.11
Classifier: Programming Language :: Python :: 3.12
Classifier: Programming Language :: Python :: 3.13
Requires-Python: >=3.9
License-File: LICENSE
Requires-Dist: anywidget>=0.9.0
Requires-Dist: duckdb>=1.4.2
Requires-Dist: geopandas
Requires-Dist: ipyvuetify
Requires-Dist: ipywidgets>=8.0.0
Requires-Dist: numpy
Requires-Dist: pandas
Requires-Dist: psutil
Requires-Dist: pystac-client
Requires-Dist: requests
Requires-Dist: traitlets>=5.0.0
Requires-Dist: xyzservices
Provides-Extra: all
Requires-Dist: anymap[extra,raster]; extra == "all"
Provides-Extra: extra
Requires-Dist: pandas; extra == "extra"
Provides-Extra: raster
Requires-Dist: localtileserver>=0.10.6; extra == "raster"
Requires-Dist: jupyter-server-proxy; extra == "raster"
Requires-Dist: rio-cogeo; extra == "raster"
Requires-Dist: rioxarray; extra == "raster"
Requires-Dist: flask; extra == "raster"
Requires-Dist: flask-cors; extra == "raster"
Dynamic: license-file
